assumption_sheriff/__init__.py
assumption_sheriff/assumption_sheriff.py
assumption_sheriff-0.1.0.dist-info/LICENSE.txt
assumption_sheriff-0.1.0.dist-info/METADATA
assumption_sheriff-0.1.0.dist-info/WHEEL
assumption_sheriff-0.1.0.dist-info/top_level.txt
assumption_sheriff-0.1.0.dist-info/RECORD
