Metadata-Version: 2.1
Name: assumption_sheriff
Version: 0.1.0
Summary: A comprehensive statistical assumption checking package
Home-page: https://github.com/MohsenAskar
Author: Mohsen Askar
Author-email: ceaser198511@gmail.com
Classifier: Programming Language :: Python :: 3
Classifier: License :: OSI Approved :: MIT License
Classifier: Operating System :: OS Independent
Requires-Python: >=3.10
License-File: LICENSE.txt
Requires-Dist: pandas
Requires-Dist: numpy
Requires-Dist: scipy
Requires-Dist: statsmodels
Requires-Dist: lifelines
